bettercheck/__init__.py
bettercheck/check_yourself.py
bettercheck/checker.py
bettercheck/cli.py
bettercheck/dep_tree.py
bettercheck/report_utils.py
bettercheck/scanner.py
bettercheck/security.py
bettercheck-0.0.1.dist-info/LICENSE
bettercheck-0.0.1.dist-info/METADATA
bettercheck-0.0.1.dist-info/WHEEL
bettercheck-0.0.1.dist-info/entry_points.txt
bettercheck-0.0.1.dist-info/top_level.txt
bettercheck-0.0.1.dist-info/RECORD
