Metadata-Version: 2.1
Name: bettercheck
Version: 0.0.1
Summary: A CLI tool that helps evaluate Python packages for security concerns
Author-email: Jason Pickup <therayking99@gmail.com>
Project-URL: Homepage, https://github.com/rayking99/bettercheck
Project-URL: Repository, https://github.com/rayking99/bettercheck.git
Keywords: security,package,dependency,check,vulnerability
Classifier: License :: OSI Approved :: MIT License
Classifier: Programming Language :: Python :: 3
Classifier: Programming Language :: Python :: 3.8
Classifier: Programming Language :: Python :: 3.9
Classifier: Programming Language :: Python :: 3.10
Classifier: Programming Language :: Python :: 3.11
Classifier: Programming Language :: Python :: 3.12
Classifier: Programming Language :: Python :: 3.13
Requires-Python: >=3.8
License-File: LICENSE
Requires-Dist: requests
Requires-Dist: click
Requires-Dist: packaging
Requires-Dist: pygithub
Requires-Dist: pypistats
Requires-Dist: jsonschema
Requires-Dist: aiohttp
Requires-Dist: dataclasses
Requires-Dist: setuptools
Provides-Extra: dev
Requires-Dist: pytest>=7.0.0; extra == "dev"
Requires-Dist: pytest-cov>=4.0.0; extra == "dev"
Requires-Dist: pytest-asyncio; extra == "dev"
Requires-Dist: black; extra == "dev"
Requires-Dist: flake8; extra == "dev"
Requires-Dist: twine; extra == "dev"
Requires-Dist: build; extra == "dev"
Requires-Dist: vcrpy; extra == "dev"
